djangoldp_uploader/__init__.py
djangoldp_uploader/apps.py
djangoldp_uploader/djangoldp_urls.py
djangoldp_uploader/forms.py
djangoldp_uploader/models.py
djangoldp_uploader/views.py
djangoldp_uploader/migrations/0001_initial.py
djangoldp_uploader/migrations/0002_document_urlid.py
djangoldp_uploader/migrations/0003_auto_20200522_1521.py
djangoldp_uploader/migrations/0004_auto_20200610_1323.py
djangoldp_uploader/migrations/0005_auto_20200619_0811.py
djangoldp_uploader/migrations/0006_file.py
djangoldp_uploader/migrations/0007_auto_20210128_0724.py
djangoldp_uploader/migrations/0008_auto_20210202_1058.py
djangoldp_uploader/migrations/0009_auto_20210202_1510.py
djangoldp_uploader/migrations/0010_auto_20210208_0918.py
djangoldp_uploader/migrations/0011_auto_20210208_1801.py
djangoldp_uploader/migrations/0012_file_document.py
djangoldp_uploader/migrations/0013_auto_20210210_0913.py
djangoldp_uploader/migrations/0014_auto_20210216_1644.py
djangoldp_uploader/migrations/0015_alter_document_options_alter_file_options_and_more.py
djangoldp_uploader/migrations/__init__.py
djangoldp_uploader/templates/demo_sib.html
djangoldp_uploader/templates/home.html
djangoldp_uploader/templates/model_form_upload.html
djangoldp_uploader/templates/sib_base.html
djangoldp_uploader/templates/simple_upload.html
djangoldp_uploader/tests/__init__.py
djangoldp_uploader/tests/runner.py
djangoldp_uploader/tests/tests_upload.py
djangoldp_uploader-3.0.1.dist-info/METADATA
djangoldp_uploader-3.0.1.dist-info/WHEEL
djangoldp_uploader-3.0.1.dist-info/top_level.txt
djangoldp_uploader-3.0.1.dist-info/RECORD
